goalzero/__init__.py
goalzero/exceptions.py
goalzero-0.2.2.dist-info/LICENSE
goalzero-0.2.2.dist-info/METADATA
goalzero-0.2.2.dist-info/WHEEL
goalzero-0.2.2.dist-info/top_level.txt
goalzero-0.2.2.dist-info/RECORD
