Metadata-Version: 2.1
Name: goalzero
Version: 0.2.2
Summary: Goal Zero REST Api Library
Home-page: https://github.com/tkdrob/goalzero
Author: Robert Hillis
Author-email: tkdrob4390@yahoo.com
Classifier: Programming Language :: Python :: 3
Classifier: License :: OSI Approved :: MIT License
Classifier: Operating System :: OS Independent
Requires-Python: >=3.6
License-File: LICENSE
